LICENSE
MANIFEST.in
README.md
setup.py
django_fas.egg-info/PKG-INFO
django_fas.egg-info/SOURCES.txt
django_fas.egg-info/dependency_links.txt
django_fas.egg-info/top_level.txt
fas/__init__.py
fas/backend.py
fas/consumer.py
fas/urls.py
fas/views.py