Metadata-Version: 1.1
Name: django-fas
Version: 1.1.0
Summary: Django auth backend for FAS (Fedora Accounts System)
Home-page: https://github.com/misli/django-fas
Author: Jakub Dorňák
Author-email: jdornak@redhat.com
License: BSD
Platform: UNKNOWN
Classifier: Development Status :: 5 - Production/Stable
Classifier: Environment :: Web Environment
Classifier: Intended Audience :: Developers
Classifier: Intended Audience :: System Administrators
Classifier: License :: OSI Approved :: BSD License
Classifier: Operating System :: MacOS :: MacOS X
Classifier: Operating System :: Microsoft :: Windows
Classifier: Operating System :: POSIX
Classifier: Programming Language :: Python
Classifier: Programming Language :: Python :: 2.7
Classifier: Programming Language :: Python :: 3.4
